bakalari_token.py
bakalari_token-2.0.post1.dist-info/LICENSE
bakalari_token-2.0.post1.dist-info/METADATA
bakalari_token-2.0.post1.dist-info/WHEEL
bakalari_token-2.0.post1.dist-info/entry_points.txt
bakalari_token-2.0.post1.dist-info/top_level.txt
bakalari_token-2.0.post1.dist-info/RECORD
