Metadata-Version: 2.1
Name: bakalari-token
Version: 2.0.post1
Summary: Jednoduchý Python script pro vygenerování tokenu pro Bakaláři API.
Home-page: https://github.com/bakalari-api/python-token-generator
Author: Marian Šámal
Author-email: margotka000@gmail.com
License: MIT License
Project-URL: Documentation, https://github.com/bakalari-api/python-token-generator/blob/master/README.md#návod
Project-URL: Code, https://github.com/bakalari-api/python-token-generator
Project-URL: Issue tracker, https://github.com/bakalari-api/python-token-generator/issues
Platform: UNKNOWN
Classifier: Development Status :: 5 - Production/Stable
Classifier: Environment :: Console
Classifier: Intended Audience :: Developers
Classifier: License :: OSI Approved :: MIT License
Classifier: Natural Language :: Czech
Classifier: Operating System :: OS Independent
Classifier: Programming Language :: Python :: 3 :: Only
Classifier: Topic :: Education
Requires-Python: >=3.6
